{"metadata": {"dbt_schema_version": "https://schemas.getdbt.com/dbt/run-results/v4.json", "dbt_version": "1.0.5", "generated_at": "2022-04-24T19:05:57.418883Z", "invocation_id": "413cb7ea-c4b4-4d5f-b1f9-6ff889d7f71c", "env": {}}, "results": [{"status": "success", "timing": [{"name": "compile", "started_at": "2022-04-24T19:05:50.956221Z", "completed_at": "2022-04-24T19:05:50.973936Z"}, {"name": "execute", "started_at": "2022-04-24T19:05:50.974248Z", "completed_at": "2022-04-24T19:05:52.457121Z"}], "thread_id": "Thread-2", "execution_time": 1.698671579360962, "adapter_response": {"_message": "SUCCESS 1", "code": "SUCCESS", "rows_affected": 1}, "message": "SUCCESS 1", "failures": null, "unique_id": "model.my_new_project.stg_addresses"}, {"status": "success", "timing": [{"name": "compile", "started_at": "2022-04-24T19:05:50.960365Z", "completed_at": "2022-04-24T19:05:51.005654Z"}, {"name": "execute", "started_at": "2022-04-24T19:05:51.006048Z", "completed_at": "2022-04-24T19:05:52.518337Z"}], "thread_id": "Thread-3", "execution_time": 1.7335851192474365, "adapter_response": {"_message": "SUCCESS 1", "code": "SUCCESS", "rows_affected": 1}, "message": "SUCCESS 1", "failures": null, "unique_id": "model.my_new_project.stg_devices"}, {"status": "success", "timing": [{"name": "compile", "started_at": "2022-04-24T19:05:50.955210Z", "completed_at": "2022-04-24T19:05:51.028106Z"}, {"name": "execute", "started_at": "2022-04-24T19:05:51.028435Z", "completed_at": "2022-04-24T19:05:52.545136Z"}], "thread_id": "Thread-1", "execution_time": 1.7661983966827393, "adapter_response": {"_message": "SUCCESS 1", "code": "SUCCESS", "rows_affected": 1}, "message": "SUCCESS 1", "failures": null, "unique_id": "model.my_new_project.orginal_query"}, {"status": "success", "timing": [{"name": "compile", "started_at": "2022-04-24T19:05:50.963844Z", "completed_at": "2022-04-24T19:05:50.979334Z"}, {"name": "execute", "started_at": "2022-04-24T19:05:50.979612Z", "completed_at": "2022-04-24T19:05:52.586083Z"}], "thread_id": "Thread-4", "execution_time": 1.8120899200439453, "adapter_response": {"_message": "SUCCESS 1", "code": "SUCCESS", "rows_affected": 1}, "message": "SUCCESS 1", "failures": null, "unique_id": "model.my_new_project.stg_orders"}, {"status": "success", "timing": [{"name": "compile", "started_at": "2022-04-24T19:05:52.777040Z", "completed_at": "2022-04-24T19:05:52.793719Z"}, {"name": "execute", "started_at": "2022-04-24T19:05:52.794024Z", "completed_at": "2022-04-24T19:05:53.856397Z"}], "thread_id": "Thread-4", "execution_time": 1.2551953792572021, "adapter_response": {"_message": "SUCCESS 1", "code": "SUCCESS", "rows_affected": 1}, "message": "SUCCESS 1", "failures": null, "unique_id": "model.my_new_project.intr_device_orders"}, {"status": "success", "timing": [{"name": "compile", "started_at": "2022-04-24T19:05:52.722478Z", "completed_at": "2022-04-24T19:05:52.740122Z"}, {"name": "execute", "started_at": "2022-04-24T19:05:52.740468Z", "completed_at": "2022-04-24T19:05:53.848360Z"}], "thread_id": "Thread-1", "execution_time": 1.3163986206054688, "adapter_response": {"_message": "SUCCESS 1", "code": "SUCCESS", "rows_affected": 1}, "message": "SUCCESS 1", "failures": null, "unique_id": "model.my_new_project.intr_ctry_type"}, {"status": "success", "timing": [{"name": "compile", "started_at": "2022-04-24T19:05:52.656170Z", "completed_at": "2022-04-24T19:05:52.673033Z"}, {"name": "execute", "started_at": "2022-04-24T19:05:52.673434Z", "completed_at": "2022-04-24T19:05:53.851285Z"}], "thread_id": "Thread-2", "execution_time": 1.3852787017822266, "adapter_response": {"_message": "SUCCESS 1", "code": "SUCCESS", "rows_affected": 1}, "message": "SUCCESS 1", "failures": null, "unique_id": "model.my_new_project.stg_payments"}, {"status": "success", "timing": [{"name": "compile", "started_at": "2022-04-24T19:05:52.695138Z", "completed_at": "2022-04-24T19:05:52.723856Z"}, {"name": "execute", "started_at": "2022-04-24T19:05:52.724147Z", "completed_at": "2022-04-24T19:05:53.916502Z"}], "thread_id": "Thread-3", "execution_time": 1.4106051921844482, "adapter_response": {"_message": "SUCCESS 1", "code": "SUCCESS", "rows_affected": 1}, "message": "SUCCESS 1", "failures": null, "unique_id": "model.my_new_project.stg_query"}, {"status": "success", "timing": [{"name": "compile", "started_at": "2022-04-24T19:05:54.033527Z", "completed_at": "2022-04-24T19:05:54.051524Z"}, {"name": "execute", "started_at": "2022-04-24T19:05:54.051803Z", "completed_at": "2022-04-24T19:05:54.929909Z"}], "thread_id": "Thread-4", "execution_time": 1.0882279872894287, "adapter_response": {"_message": "SUCCESS 1", "code": "SUCCESS", "rows_affected": 1}, "message": "SUCCESS 1", "failures": null, "unique_id": "model.my_new_project.intr_first_order"}, {"status": "success", "timing": [{"name": "compile", "started_at": "2022-04-24T19:05:54.042803Z", "completed_at": "2022-04-24T19:05:54.059119Z"}, {"name": "execute", "started_at": "2022-04-24T19:05:54.059509Z", "completed_at": "2022-04-24T19:05:54.982320Z"}], "thread_id": "Thread-1", "execution_time": 1.1502366065979004, "adapter_response": {"_message": "SUCCESS 1", "code": "SUCCESS", "rows_affected": 1}, "message": "SUCCESS 1", "failures": null, "unique_id": "model.my_new_project.intr_payments"}, {"status": "success", "timing": [{"name": "compile", "started_at": "2022-04-24T19:05:55.123474Z", "completed_at": "2022-04-24T19:05:55.138288Z"}, {"name": "execute", "started_at": "2022-04-24T19:05:55.138592Z", "completed_at": "2022-04-24T19:05:55.992870Z"}], "thread_id": "Thread-2", "execution_time": 1.157508134841919, "adapter_response": {"_message": "SUCCESS 1", "code": "SUCCESS", "rows_affected": 1}, "message": "SUCCESS 1", "failures": null, "unique_id": "model.my_new_project.intr_user_type"}, {"status": "success", "timing": [{"name": "compile", "started_at": "2022-04-24T19:05:56.283111Z", "completed_at": "2022-04-24T19:05:56.299512Z"}, {"name": "execute", "started_at": "2022-04-24T19:05:56.299784Z", "completed_at": "2022-04-24T19:05:57.232360Z"}], "thread_id": "Thread-4", "execution_time": 1.132810115814209, "adapter_response": {"_message": "SUCCESS 1", "code": "SUCCESS", "rows_affected": 1}, "message": "SUCCESS 1", "failures": null, "unique_id": "model.my_new_project.fct_final"}], "elapsed_time": 9.123680830001831, "args": {"write_json": true, "use_colors": true, "printer_width": 80, "version_check": true, "partial_parse": true, "static_parser": true, "profiles_dir": "/usr/src/develop/.dbt", "send_anonymous_usage_stats": true, "event_buffer_size": 100000, "vars": "{}\n", "which": "run", "rpc_method": "run", "indirect_selection": "eager"}}